flask_lnd.py
Flask_LND-0.0.1.dist-info/LICENSE
Flask_LND-0.0.1.dist-info/METADATA
Flask_LND-0.0.1.dist-info/WHEEL
Flask_LND-0.0.1.dist-info/top_level.txt
Flask_LND-0.0.1.dist-info/RECORD
