Metadata-Version: 2.1
Name: Flask-LND
Version: 0.0.1
Summary: An LND gRPC interface for Flask
Home-page: https://github.com/bitstein/flask-lnd
Author: Michael Goldstein
Author-email: michael@bitstein.org
License: MIT
Keywords: lnd grpc flask
Platform: any
Classifier: Programming Language :: Python :: 3
Classifier: License :: OSI Approved :: MIT License
Classifier: Operating System :: OS Independent
Requires-Dist: Flask
Requires-Dist: lnd-grpc
